[{"year":1900,"co2":0.0,"methane":0.808,"gdp":0.0,"population":269139.0},{"year":1901,"co2":0.0,"methane":0.801,"gdp":0.0,"population":267921.0},{"year":1902,"co2":0.0,"methane":0.794,"gdp":0.0,"population":266708.0},{"year":1903,"co2":0.0,"methane":0.787,"gdp":0.0,"population":265500.0},{"year":1904,"co2":0.0,"methane":0.781,"gdp":0.0,"population":264298.0},{"year":1905,"co2":0.0,"methane":0.774,"gdp":0.0,"population":263101.0},{"year":1906,"co2":0.0,"methane":0.768,"gdp":0.0,"population":261910.0},{"year":1907,"co2":0.0,"methane":0.762,"gdp":0.0,"population":260723.0},{"year":1908,"co2":0.0,"methane":0.756,"gdp":0.0,"population":259543.0},{"year":1909,"co2":0.0,"methane":0.75,"gdp":0.0,"population":258624.0},{"year":1910,"co2":0.0,"methane":0.744,"gdp":0.0,"population":257966.0},{"year":1911,"co2":0.0,"methane":0.743,"gdp":0.0,"population":257568.0},{"year":1912,"co2":0.0,"methane":0.742,"gdp":0.0,"population":257430.0},{"year":1913,"co2":0.0,"methane":0.741,"gdp":0.0,"population":257550.0},{"year":1914,"co2":0.0,"methane":0.741,"gdp":0.0,"population":257670.0},{"year":1915,"co2":0.0,"methane":0.74,"gdp":0.0,"population":257789.0},{"year":1916,"co2":0.0,"methane":0.739,"gdp":0.0,"population":257909.0},{"year":1917,"co2":0.0,"methane":0.739,"gdp":0.0,"population":258029.0},{"year":1918,"co2":0.0,"methane":0.739,"gdp":0.0,"population":258029.0},{"year":1919,"co2":0.0,"methane":0.739,"gdp":0.0,"population":258029.0},{"year":1920,"co2":0.0,"methane":0.738,"gdp":0.0,"population":258029.0},{"year":1921,"co2":0.0,"methane":0.728,"gdp":0.0,"population":258029.0},{"year":1922,"co2":0.0,"methane":0.717,"gdp":0.0,"population":258029.0},{"year":1923,"co2":0.0,"methane":0.708,"gdp":0.0,"population":258029.0},{"year":1924,"co2":0.0,"methane":0.698,"gdp":0.0,"population":258029.0},{"year":1925,"co2":0.0,"methane":0.689,"gdp":0.0,"population":258029.0},{"year":1926,"co2":0.0,"methane":0.68,"gdp":0.0,"population":258029.0},{"year":1927,"co2":0.0,"methane":0.672,"gdp":0.0,"population":258029.0},{"year":1928,"co2":0.0,"methane":0.664,"gdp":0.0,"population":258029.0},{"year":1929,"co2":0.0,"methane":0.657,"gdp":0.0,"population":258029.0},{"year":1930,"co2":0.0,"methane":0.65,"gdp":0.0,"population":258029.0},{"year":1931,"co2":0.0,"methane":0.646,"gdp":0.0,"population":258029.0},{"year":1932,"co2":0.0,"methane":0.642,"gdp":0.0,"population":258029.0},{"year":1933,"co2":0.0,"methane":0.639,"gdp":0.0,"population":258029.0},{"year":1934,"co2":0.0,"methane":0.636,"gdp":0.0,"population":258029.0},{"year":1935,"co2":0.0,"methane":0.633,"gdp":0.0,"population":258029.0},{"year":1936,"co2":0.0,"methane":0.631,"gdp":0.0,"population":258029.0},{"year":1937,"co2":0.0,"methane":0.63,"gdp":0.0,"population":258029.0},{"year":1938,"co2":0.0,"methane":0.628,"gdp":0.0,"population":258029.0},{"year":1939,"co2":0.0,"methane":0.627,"gdp":0.0,"population":255899.0},{"year":1940,"co2":0.0,"methane":0.626,"gdp":0.0,"population":251726.0},{"year":1941,"co2":0.0,"methane":0.635,"gdp":0.0,"population":245595.0},{"year":1942,"co2":0.0,"methane":0.645,"gdp":0.0,"population":237586.0},{"year":1943,"co2":0.0,"methane":0.655,"gdp":0.0,"population":227778.0},{"year":1944,"co2":0.0,"methane":0.666,"gdp":0.0,"population":218374.0},{"year":1945,"co2":0.0,"methane":0.664,"gdp":0.0,"population":209359.0},{"year":1946,"co2":0.0,"methane":0.662,"gdp":0.0,"population":200716.0},{"year":1947,"co2":0.0,"methane":0.66,"gdp":0.0,"population":192430.0},{"year":1948,"co2":0.0,"methane":0.658,"gdp":0.0,"population":184486.0},{"year":1949,"co2":0.0,"methane":0.656,"gdp":0.0,"population":179148.0},{"year":1950,"co2":0.0,"methane":0.654,"gdp":0.0,"population":169991.0},{"year":1951,"co2":0.0,"methane":0.637,"gdp":0.0,"population":174615.0},{"year":1952,"co2":0.0,"methane":0.621,"gdp":0.0,"population":179392.0},{"year":1953,"co2":0.0,"methane":0.607,"gdp":0.0,"population":184345.0},{"year":1954,"co2":0.0,"methane":0.594,"gdp":0.0,"population":189467.0},{"year":1955,"co2":0.0,"methane":0.581,"gdp":0.0,"population":194759.0},{"year":1956,"co2":0.0,"methane":0.569,"gdp":0.0,"population":200245.0},{"year":1957,"co2":0.0,"methane":0.559,"gdp":0.0,"population":205913.0},{"year":1958,"co2":0.0,"methane":0.548,"gdp":0.0,"population":211766.0},{"year":1959,"co2":0.0,"methane":0.538,"gdp":0.0,"population":217827.0},{"year":1960,"co2":0.0,"methane":0.529,"gdp":0.0,"population":224098.0},{"year":1961,"co2":0.0,"methane":0.518,"gdp":0.0,"population":230617.0},{"year":1962,"co2":0.0,"methane":0.51,"gdp":0.0,"population":237648.0},{"year":1963,"co2":0.0,"methane":0.501,"gdp":0.0,"population":245168.0},{"year":1964,"co2":0.0,"methane":0.494,"gdp":0.0,"population":252997.0},{"year":1965,"co2":0.0,"methane":0.486,"gdp":0.0,"population":261210.0},{"year":1966,"co2":0.0,"methane":0.477,"gdp":0.0,"population":269830.0},{"year":1967,"co2":0.0,"methane":0.47,"gdp":0.0,"population":278855.0},{"year":1968,"co2":0.0,"methane":0.462,"gdp":0.0,"population":288320.0},{"year":1969,"co2":0.0,"methane":0.458,"gdp":0.0,"population":298220.0},{"year":1970,"co2":0.004,"methane":0.476,"gdp":0.0,"population":308536.0},{"year":1971,"co2":0.004,"methane":0.485,"gdp":0.0,"population":319219.0},{"year":1972,"co2":0.004,"methane":0.495,"gdp":0.0,"population":330265.0},{"year":1973,"co2":0.004,"methane":0.505,"gdp":0.0,"population":341713.0},{"year":1974,"co2":0.004,"methane":0.517,"gdp":0.0,"population":353548.0},{"year":1975,"co2":0.004,"methane":0.527,"gdp":0.0,"population":365800.0},{"year":1976,"co2":0.004,"methane":0.542,"gdp":0.0,"population":378499.0},{"year":1977,"co2":0.007,"methane":0.556,"gdp":0.0,"population":391649.0},{"year":1978,"co2":0.011,"methane":0.576,"gdp":0.0,"population":405256.0},{"year":1979,"co2":0.022,"methane":0.591,"gdp":0.0,"population":419208.0},{"year":1980,"co2":0.022,"methane":0.606,"gdp":0.0,"population":433412.0},{"year":1981,"co2":0.055,"methane":0.62,"gdp":0.0,"population":447851.0},{"year":1982,"co2":0.063,"methane":0.641,"gdp":0.0,"population":462495.0},{"year":1983,"co2":0.087,"methane":0.665,"gdp":0.0,"population":477473.0},{"year":1984,"co2":0.109,"methane":0.686,"gdp":0.0,"population":492794.0},{"year":1985,"co2":0.12,"methane":0.718,"gdp":0.0,"population":508399.0},{"year":1986,"co2":0.112,"methane":0.731,"gdp":0.0,"population":524327.0},{"year":1987,"co2":0.16,"methane":0.754,"gdp":0.0,"population":540570.0},{"year":1988,"co2":0.167,"methane":0.726,"gdp":0.0,"population":557002.0},{"year":1989,"co2":0.12,"methane":0.735,"gdp":0.0,"population":573593.0},{"year":1990,"co2":0.186,"methane":0.886,"gdp":0.0,"population":589295.0},{"year":1991,"co2":0.186,"methane":0.784,"gdp":0.0,"population":599789.0},{"year":1992,"co2":0.215,"methane":0.753,"gdp":0.0,"population":577780.0},{"year":1993,"co2":0.182,"methane":0.762,"gdp":0.0,"population":554680.0},{"year":1994,"co2":0.212,"methane":0.767,"gdp":0.0,"population":554509.0},{"year":1995,"co2":0.249,"methane":0.852,"gdp":0.0,"population":547995.0},{"year":1996,"co2":0.298,"methane":0.837,"gdp":0.0,"population":548792.0},{"year":1997,"co2":0.39,"methane":0.831,"gdp":0.0,"population":558698.0},{"year":1998,"co2":0.385,"methane":0.829,"gdp":0.0,"population":569439.0},{"year":1999,"co2":0.386,"methane":0.851,"gdp":0.0,"population":582589.0},{"year":2000,"co2":0.397,"methane":0.853,"gdp":0.0,"population":596871.0},{"year":2001,"co2":0.464,"methane":0.832,"gdp":0.0,"population":610801.0},{"year":2002,"co2":0.494,"methane":0.833,"gdp":0.0,"population":624417.0},{"year":2003,"co2":0.494,"methane":0.842,"gdp":0.0,"population":637667.0},{"year":2004,"co2":0.436,"methane":0.841,"gdp":0.0,"population":650559.0},{"year":2005,"co2":0.546,"methane":0.925,"gdp":0.0,"population":661875.0},{"year":2006,"co2":0.411,"methane":0.99,"gdp":0.0,"population":670803.0},{"year":2007,"co2":0.397,"methane":1.001,"gdp":0.0,"population":678643.0},{"year":2008,"co2":0.646,"methane":1.029,"gdp":0.0,"population":686359.0},{"year":2009,"co2":0.683,"methane":0.985,"gdp":0.0,"population":693994.0},{"year":2010,"co2":0.905,"methane":1.0,"gdp":0.0,"population":701638.0},{"year":2011,"co2":1.007,"methane":1.02,"gdp":0.0,"population":709387.0},{"year":2012,"co2":1.15,"methane":1.013,"gdp":0.0,"population":717288.0},{"year":2013,"co2":1.269,"methane":1.075,"gdp":0.0,"population":725282.0},{"year":2014,"co2":1.332,"methane":1.097,"gdp":0.0,"population":733151.0},{"year":2015,"co2":1.434,"methane":1.107,"gdp":0.0,"population":740623.0},{"year":2016,"co2":1.56,"methane":1.147,"gdp":0.0,"population":747878.0},{"year":2017,"co2":1.649,"methane":1.179,"gdp":0.0,"population":754343.0},{"year":2018,"co2":1.682,"methane":1.208,"gdp":0.0,"population":759766.0},{"year":2019,"co2":1.565,"methane":1.213,"gdp":0.0,"population":764830.0},{"year":2020,"co2":1.214,"methane":1.172,"gdp":0.0,"population":770013.0},{"year":2021,"co2":1.455,"methane":1.167,"gdp":0.0,"population":775450.0},{"year":2022,"co2":1.55,"methane":1.142,"gdp":0.0,"population":780921.0},{"year":2023,"co2":1.63,"methane":1.126,"gdp":0.0,"population":786386.0},{"year":2024,"co2":1.657,"methane":1.103,"gdp":0.0,"population":791530.0}]