[{"year":1900,"co2":0.0,"methane":16.83,"gdp":0.0,"population":17719308.0},{"year":1901,"co2":0.0,"methane":16.993,"gdp":0.0,"population":17705014.0},{"year":1902,"co2":0.0,"methane":17.157,"gdp":0.0,"population":17690721.0},{"year":1903,"co2":0.0,"methane":17.321,"gdp":0.0,"population":17676427.0},{"year":1904,"co2":0.0,"methane":17.486,"gdp":0.0,"population":17662133.0},{"year":1905,"co2":0.0,"methane":17.651,"gdp":0.0,"population":17647839.0},{"year":1906,"co2":0.0,"methane":17.816,"gdp":0.0,"population":17633545.0},{"year":1907,"co2":0.0,"methane":17.982,"gdp":0.0,"population":17619251.0},{"year":1908,"co2":0.0,"methane":18.148,"gdp":0.0,"population":17604958.0},{"year":1909,"co2":0.0,"methane":18.314,"gdp":0.0,"population":17590664.0},{"year":1910,"co2":0.0,"methane":18.481,"gdp":0.0,"population":17576370.0},{"year":1911,"co2":0.0,"methane":18.648,"gdp":0.0,"population":17562076.0},{"year":1912,"co2":0.0,"methane":18.816,"gdp":0.0,"population":17547782.0},{"year":1913,"co2":0.0,"methane":18.984,"gdp":0.0,"population":17533488.0},{"year":1914,"co2":0.0,"methane":19.149,"gdp":0.0,"population":17519195.0},{"year":1915,"co2":0.0,"methane":19.314,"gdp":0.0,"population":17504901.0},{"year":1916,"co2":0.0,"methane":19.479,"gdp":0.0,"population":17490607.0},{"year":1917,"co2":0.0,"methane":19.645,"gdp":0.0,"population":17476313.0},{"year":1918,"co2":0.0,"methane":19.811,"gdp":0.0,"population":17476313.0},{"year":1919,"co2":0.0,"methane":19.978,"gdp":0.0,"population":17476313.0},{"year":1920,"co2":0.0,"methane":20.133,"gdp":0.0,"population":17476313.0},{"year":1921,"co2":0.0,"methane":20.298,"gdp":0.0,"population":17476313.0},{"year":1922,"co2":0.0,"methane":20.464,"gdp":0.0,"population":17476313.0},{"year":1923,"co2":0.0,"methane":20.629,"gdp":0.0,"population":17476313.0},{"year":1924,"co2":0.0,"methane":20.795,"gdp":0.0,"population":17476313.0},{"year":1925,"co2":0.0,"methane":20.961,"gdp":0.0,"population":17476313.0},{"year":1926,"co2":0.0,"methane":21.127,"gdp":0.0,"population":17476313.0},{"year":1927,"co2":0.0,"methane":21.293,"gdp":0.0,"population":17476313.0},{"year":1928,"co2":0.0,"methane":21.46,"gdp":0.0,"population":17476313.0},{"year":1929,"co2":0.0,"methane":21.626,"gdp":0.0,"population":17476313.0},{"year":1930,"co2":0.0,"methane":21.793,"gdp":0.0,"population":17476313.0},{"year":1931,"co2":0.0,"methane":21.96,"gdp":0.0,"population":17476313.0},{"year":1932,"co2":0.0,"methane":22.127,"gdp":0.0,"population":17476313.0},{"year":1933,"co2":0.0,"methane":22.295,"gdp":0.0,"population":17476313.0},{"year":1934,"co2":0.0,"methane":22.462,"gdp":0.0,"population":17476313.0},{"year":1935,"co2":0.0,"methane":22.63,"gdp":0.0,"population":17476313.0},{"year":1936,"co2":0.0,"methane":22.96,"gdp":0.0,"population":17476313.0},{"year":1937,"co2":0.0,"methane":23.293,"gdp":0.0,"population":17476313.0},{"year":1938,"co2":0.0,"methane":23.628,"gdp":0.0,"population":17476313.0},{"year":1939,"co2":0.0,"methane":23.967,"gdp":0.0,"population":17476313.0},{"year":1940,"co2":0.0,"methane":24.307,"gdp":0.0,"population":17476313.0},{"year":1941,"co2":0.011,"methane":24.653,"gdp":0.0,"population":17476313.0},{"year":1942,"co2":0.011,"methane":25.0,"gdp":0.0,"population":17476313.0},{"year":1943,"co2":0.011,"methane":25.351,"gdp":0.0,"population":17476313.0},{"year":1944,"co2":0.0,"methane":25.704,"gdp":0.0,"population":17476313.0},{"year":1945,"co2":0.0,"methane":26.068,"gdp":0.0,"population":17476313.0},{"year":1946,"co2":0.0,"methane":26.434,"gdp":0.0,"population":17476313.0},{"year":1947,"co2":0.0,"methane":26.841,"gdp":0.0,"population":17476313.0},{"year":1948,"co2":0.004,"methane":27.254,"gdp":0.0,"population":17476313.0},{"year":1949,"co2":0.004,"methane":27.672,"gdp":0.0,"population":17553622.0},{"year":1950,"co2":0.088,"methane":28.101,"gdp":12816444847.0,"population":17670418.0},{"year":1951,"co2":0.062,"methane":28.821,"gdp":13194631406.0,"population":17989060.0},{"year":1952,"co2":0.099,"methane":29.569,"gdp":13543810054.0,"population":18326176.0},{"year":1953,"co2":0.183,"methane":30.344,"gdp":14338910949.0,"population":18674772.0},{"year":1954,"co2":0.271,"methane":31.145,"gdp":14324960253.0,"population":19038036.0},{"year":1955,"co2":0.227,"methane":31.971,"gdp":15096087974.0,"population":19419768.0},{"year":1956,"co2":0.242,"methane":32.831,"gdp":15575803718.0,"population":19818886.0},{"year":1957,"co2":0.322,"methane":33.726,"gdp":15468633837.0,"population":20173747.0},{"year":1958,"co2":0.319,"methane":34.661,"gdp":15973565679.0,"population":20480281.0},{"year":1959,"co2":0.337,"methane":35.644,"gdp":16448278125.0,"population":20878098.0},{"year":1960,"co2":0.352,"methane":36.683,"gdp":17260063074.0,"population":21376688.0},{"year":1961,"co2":0.341,"methane":37.441,"gdp":18125804359.0,"population":21906102.0},{"year":1962,"co2":0.396,"methane":37.876,"gdp":18844801312.0,"population":22465125.0},{"year":1963,"co2":0.421,"methane":38.261,"gdp":21366755925.0,"population":23051639.0},{"year":1964,"co2":0.407,"methane":38.676,"gdp":22389040078.0,"population":23666547.0},{"year":1965,"co2":0.644,"methane":39.101,"gdp":23721571218.0,"population":24310615.0},{"year":1966,"co2":0.824,"methane":39.553,"gdp":24660953250.0,"population":24952691.0},{"year":1967,"co2":1.073,"methane":39.939,"gdp":25707798964.0,"population":25620283.0},{"year":1968,"co2":1.725,"methane":40.337,"gdp":26106776265.0,"population":26337933.0},{"year":1969,"co2":1.666,"methane":40.71,"gdp":27119812917.0,"population":27072575.0},{"year":1970,"co2":1.652,"methane":41.075,"gdp":28633734539.0,"population":27829135.0},{"year":1971,"co2":1.849,"methane":41.483,"gdp":29865520609.0,"population":28600114.0},{"year":1972,"co2":1.406,"methane":41.342,"gdp":31385113984.0,"population":29374611.0},{"year":1973,"co2":1.751,"methane":42.219,"gdp":32393312882.0,"population":30166789.0},{"year":1974,"co2":1.736,"methane":41.77,"gdp":32791202859.0,"population":30957277.0},{"year":1975,"co2":1.209,"methane":41.089,"gdp":32856117328.0,"population":31723255.0},{"year":1976,"co2":1.175,"methane":40.937,"gdp":33758170375.0,"population":32534428.0},{"year":1977,"co2":1.047,"methane":41.687,"gdp":34642511796.0,"population":33167276.0},{"year":1978,"co2":1.369,"methane":41.53,"gdp":34323218343.0,"population":33734601.0},{"year":1979,"co2":1.844,"methane":41.937,"gdp":36463055132.0,"population":34238655.0},{"year":1980,"co2":1.817,"methane":42.423,"gdp":38082969410.0,"population":34428515.0},{"year":1981,"co2":1.86,"methane":42.253,"gdp":38888412914.0,"population":35304010.0},{"year":1982,"co2":1.474,"methane":43.2,"gdp":39483909062.0,"population":36701293.0},{"year":1983,"co2":1.835,"methane":44.27,"gdp":41460915550.0,"population":37740821.0},{"year":1984,"co2":1.65,"methane":43.419,"gdp":40637087843.0,"population":38735728.0},{"year":1985,"co2":1.799,"methane":45.134,"gdp":37958074687.0,"population":39842136.0},{"year":1986,"co2":2.195,"methane":47.256,"gdp":40403510625.0,"population":41037658.0},{"year":1987,"co2":2.554,"methane":45.345,"gdp":44197123359.0,"population":42460039.0},{"year":1988,"co2":2.64,"methane":45.555,"gdp":45041421375.0,"population":44150834.0},{"year":1989,"co2":2.794,"methane":47.84,"gdp":45764085968.0,"population":45879686.0},{"year":1990,"co2":2.987,"methane":49.368,"gdp":45030920800.0,"population":47609760.0},{"year":1991,"co2":2.958,"methane":50.001,"gdp":41447817951.0,"population":49717203.0},{"year":1992,"co2":2.937,"methane":51.85,"gdp":37455354506.0,"population":51853756.0},{"year":1993,"co2":2.994,"methane":47.881,"gdp":37874279529.0,"population":53708892.0},{"year":1994,"co2":2.197,"methane":49.347,"gdp":40711848289.0,"population":55611514.0},{"year":1995,"co2":2.506,"methane":49.844,"gdp":42631100913.0,"population":57537340.0},{"year":1996,"co2":2.794,"methane":52.002,"gdp":46130264957.0,"population":59467640.0},{"year":1997,"co2":2.98,"methane":53.798,"gdp":49275077370.0,"population":61404541.0},{"year":1998,"co2":3.147,"methane":57.757,"gdp":48734081758.0,"population":63363523.0},{"year":1999,"co2":3.094,"methane":57.754,"gdp":48438288398.0,"population":65374561.0},{"year":2000,"co2":3.463,"methane":55.864,"gdp":50326965912.0,"population":67411496.0},{"year":2001,"co2":4.265,"methane":58.4,"gdp":52434129516.0,"population":69487767.0},{"year":2002,"co2":4.432,"methane":64.633,"gdp":54501781462.0,"population":71635521.0},{"year":2003,"co2":4.87,"methane":63.684,"gdp":53892038989.0,"population":73832664.0},{"year":2004,"co2":5.159,"methane":65.043,"gdp":55845384136.0,"population":76077211.0},{"year":2005,"co2":4.956,"methane":67.793,"gdp":61634778962.0,"population":78367476.0},{"year":2006,"co2":5.318,"methane":71.519,"gdp":67217118145.0,"population":80703495.0},{"year":2007,"co2":5.84,"methane":78.108,"gdp":73421784125.0,"population":83103218.0},{"year":2008,"co2":6.418,"methane":81.28,"gdp":79756503135.0,"population":85543670.0},{"year":2009,"co2":6.453,"methane":84.766,"gdp":86391027022.0,"population":88007641.0},{"year":2010,"co2":6.344,"methane":88.467,"gdp":94148625646.0,"population":90538518.0},{"year":2011,"co2":7.355,"methane":87.811,"gdp":104948629242.0,"population":93149977.0},{"year":2012,"co2":7.988,"methane":90.908,"gdp":116345224724.0,"population":95798771.0},{"year":2013,"co2":9.744,"methane":93.758,"gdp":128310309167.0,"population":98438752.0},{"year":2014,"co2":11.543,"methane":96.784,"gdp":141950543442.0,"population":101115615.0},{"year":2015,"co2":12.564,"methane":99.044,"gdp":157107146471.0,"population":103867140.0},{"year":2016,"co2":14.323,"methane":101.823,"gdp":173708917362.0,"population":106718163.0},{"year":2017,"co2":14.603,"methane":104.021,"gdp":190761659136.0,"population":109666482.0},{"year":2018,"co2":16.117,"methane":106.029,"gdp":206205566995.0,"population":112664157.0},{"year":2019,"co2":17.177,"methane":113.102,"gdp":221885291686.0,"population":115737384.0},{"year":2020,"co2":16.735,"methane":118.374,"gdp":237860193068.0,"population":118917670.0},{"year":2021,"co2":17.906,"methane":114.622,"gdp":251849804145.0,"population":122138588.0},{"year":2022,"co2":16.96,"methane":116.431,"gdp":269977225159.0,"population":125384285.0},{"year":2023,"co2":17.571,"methane":118.695,"gdp":0.0,"population":128691695.0},{"year":2024,"co2":17.837,"methane":119.017,"gdp":0.0,"population":132059770.0}]